xengsort/_version.py
xengsort/bitarray.py
xengsort/build.py
xengsort/classify.py
xengsort/dnaencode.py
xengsort/dnaio.py
xengsort/h5utils.py
xengsort/hash_3FCVbb.py
xengsort/hashfunctions.py
xengsort/hashio.py
xengsort/index.py
xengsort/intbitarray.py
xengsort/mathutils.py
xengsort/prefetch.py
xengsort/xengsort.py
xengsort/values/xenograft.py
xengsort_cubic-1.1.0.dist-info/LICENSE
xengsort_cubic-1.1.0.dist-info/METADATA
xengsort_cubic-1.1.0.dist-info/WHEEL
xengsort_cubic-1.1.0.dist-info/entry_points.txt
xengsort_cubic-1.1.0.dist-info/top_level.txt
xengsort_cubic-1.1.0.dist-info/RECORD
